ai_seo_strategist/__init__.py
ai_seo_strategist/main.py
ai_seo_strategist/prompts.py
ai_seo_strategist-2025.12.21130456.dist-info/METADATA
ai_seo_strategist-2025.12.21130456.dist-info/WHEEL
ai_seo_strategist-2025.12.21130456.dist-info/top_level.txt
ai_seo_strategist-2025.12.21130456.dist-info/RECORD
