Metadata-Version: 2.4
Name: ai-seo-strategist
Version: 2025.12.21130456
Summary: A new package designed to streamline the extraction and organization of AI-driven SEO strategies from user inputs. Users provide a brief description or topic related to their SEO challenges or goals,
Author-email: ai-seo-strategist <hi@eugene.plus>
License: MIT
Project-URL: Homepage, https://github.com/chigwell/ai-seo-strategist
Requires-Python: >=3.9
Requires-Dist: langchain-llm7>=0.0.0
Requires-Dist: llmatch-messages>=0.0.0
Requires-Dist: langchain-core>=0.3.0
